setup.py
binom_gaussian/Binomialdistribution.py
binom_gaussian/Gaussiandistribution.py
binom_gaussian/Generaldistribution.py
binom_gaussian/__init__.py
binom_gaussian.egg-info/PKG-INFO
binom_gaussian.egg-info/SOURCES.txt
binom_gaussian.egg-info/dependency_links.txt
binom_gaussian.egg-info/not-zip-safe
binom_gaussian.egg-info/top_level.txt