Metadata-Version: 1.0
Name: binom-gaussian
Version: 0.1
Summary: Gaussian and Binomial distributions
Home-page: UNKNOWN
Author: Author
Author-email: author@website.com
License: UNKNOWN
Platform: UNKNOWN
